shadowPaySDK/__init__.py
shadowPaySDK/const.py
shadowPaySDK/interface/__init__.py
shadowPaySDK/interface/erc20.py
shadowPaySDK/interface/erc721.py
shadowPaySDK/interface/sol.py
shadowPaySDK/types/EVMcheque.py
shadowPaySDK/types/SOLcheque.py
shadowPaySDK/types/__init__.py
shadowPaySDK/utils/__init__.py
shadowPaySDK/utils/utils.py
shadowpaysdk-1.0.1.dist-info/licenses/LICENSE
shadowpaysdk-1.0.1.dist-info/METADATA
shadowpaysdk-1.0.1.dist-info/WHEEL
shadowpaysdk-1.0.1.dist-info/top_level.txt
shadowpaysdk-1.0.1.dist-info/RECORD
